AnosysAgentsLogger/__init__.py
AnosysAgentsLogger/tracing.py
anosys_agentic_ai_package-0.0.11.dist-info/licenses/LICENSE
anosys_agentic_ai_package-0.0.11.dist-info/METADATA
anosys_agentic_ai_package-0.0.11.dist-info/WHEEL
anosys_agentic_ai_package-0.0.11.dist-info/top_level.txt
anosys_agentic_ai_package-0.0.11.dist-info/RECORD
