Metadata-Version: 2.4
Name: anosys-agentic-ai-package
Version: 0.0.11
Summary: A helper package, to support implementation to AnoSys platform easly
Author-email: Moisis Vafeiadis <moisisv@gmail.com>
License: MIT License
Project-URL: Homepage, https://anosys.ai
Requires-Python: >=3.7
License-File: LICENSE
Requires-Dist: traceAI-openai-agents>=0.1.3
Dynamic: license-file
